gcs_uri.py
gcs_uri-1.3.0.dist-info/LICENSE
gcs_uri-1.3.0.dist-info/WHEEL
gcs_uri-1.3.0.dist-info/METADATA
gcs_uri-1.3.0.dist-info/RECORD
