Metadata-Version: 2.1
Name: gcs-uri
Version: 1.3.0
Summary: Simple API to copy files to and from Google Cloud Storage
Home-page: https://github.com/andrewrosss/gcs-uri
License: MIT
Keywords: google,cloud,storage,gcp
Author: Andrew Ross
Author-email: andrew.ross.mail@gmail.com
Requires-Python: >=3.7,<4.0
Classifier: Intended Audience :: Developers
Classifier: License :: OSI Approved :: MIT License
Classifier: Operating System :: OS Independent
Classifier: Programming Language :: Python :: 3
Classifier: Programming Language :: Python :: 3.0
Classifier: Programming Language :: Python :: 3.10
Classifier: Programming Language :: Python :: 3.7
Classifier: Programming Language :: Python :: 3.8
Classifier: Programming Language :: Python :: 3.9
Classifier: Topic :: Software Development :: Libraries :: Python Modules
Classifier: Topic :: Utilities
Classifier: Typing :: Typed
Requires-Dist: google-cloud-storage (>=2.0.0,<3.0.0)
Requires-Dist: typing-extensions (>=3.10); python_version < "3.10"
Project-URL: Documentation, https://github.com/andrewrosss/gcs-uri
Project-URL: Repository, https://github.com/andrewrosss/gcs-uri
